knowme/__init__.py
knowme/__main__.py
knowme/ascii.py
knowme/installer.py
knowme/logos.py
knowme/system_info.py
knowme/utils.py
knowme-1.0.5.dist-info/licenses/LICENSE
knowme-1.0.5.dist-info/METADATA
knowme-1.0.5.dist-info/WHEEL
knowme-1.0.5.dist-info/entry_points.txt
knowme-1.0.5.dist-info/top_level.txt
knowme-1.0.5.dist-info/RECORD
