Metadata-Version: 2.4
Name: knowme
Version: 1.0.5
Summary: A fast, offline command-line tool that displays detailed system info with text-based ASCII art logos. Silent installation with progress bar!
Home-page: https://github.com/mehtahrishi/knowme
Author: Hrishi Mehta
Author-email: Hrishi Mehta <mehtahrishi45@gmail.com>
License: MIT
Project-URL: Homepage, https://github.com/mehtahrishi/knowme
Project-URL: Bug Tracker, https://github.com/mehtahrishi/knowme/issues
Project-URL: Documentation, https://github.com/mehtahrishi/knowme#readme
Project-URL: Source Code, https://github.com/mehtahrishi/knowme
Keywords: system,info,neofetch,cli,terminal,ascii,mobile,termux,android,silent
Classifier: Development Status :: 5 - Production/Stable
Classifier: Environment :: Console
Classifier: Intended Audience :: Developers
Classifier: Intended Audience :: System Administrators
Classifier: Operating System :: OS Independent
Classifier: Operating System :: POSIX :: Linux
Classifier: Operating System :: Microsoft :: Windows
Classifier: Operating System :: MacOS
Classifier: Operating System :: Android
Classifier: Programming Language :: Python :: 3
Classifier: Programming Language :: Python :: 3.7
Classifier: Programming Language :: Python :: 3.8
Classifier: Programming Language :: Python :: 3.9
Classifier: Programming Language :: Python :: 3.10
Classifier: Programming Language :: Python :: 3.11
Classifier: Programming Language :: Python :: 3.12
Classifier: Topic :: System :: Systems Administration
Classifier: Topic :: Utilities
Requires-Python: >=3.7
License-File: LICENSE
Requires-Dist: psutil>=5.8.0
Requires-Dist: distro>=1.6.0
Requires-Dist: py-cpuinfo>=8.0.0
Requires-Dist: requests>=2.25.0
Requires-Dist: gputil>=1.4.0
Requires-Dist: screeninfo>=0.6.0
Requires-Dist: ifaddr>=0.1.7
Dynamic: author
Dynamic: home-page
Dynamic: license-file
Dynamic: requires-python
